helptranslator.py
helptranslator-0.0.2.dist-info/DESCRIPTION.rst
helptranslator-0.0.2.dist-info/METADATA
helptranslator-0.0.2.dist-info/RECORD
helptranslator-0.0.2.dist-info/WHEEL
helptranslator-0.0.2.dist-info/metadata.json
helptranslator-0.0.2.dist-info/top_level.txt
