Metadata-Version: 2.0
Name: helptranslator
Version: 0.0.2
Summary: A Python module that uses Google Translate to automatically translate Python help text to any language.
Home-page: UNKNOWN
Author: Nicholas A. Del Grosso
Author-email: delgrosso.nick@gmail.com
License: BSD
Keywords: translate help python
Platform: UNKNOWN
Classifier: Topic :: Utilities
Classifier: License :: OSI Approved :: BSD License
Requires-Dist: googletrans
